{"default":{"identifier":"default","description":"Capability for the main application window","local":true,"windows":["main"],"permissions":["core:default","core:window:allow-close","core:window:allow-minimize","core:window:allow-maximize","core:window:allow-set-title","core:event:default",{"identifier":"fs:allow-read-file","allow":[{"path":"**"}]},{"identifier":"fs:allow-read-dir","allow":[{"path":"**"}]},"dialog:allow-open","dialog:allow-save","shell:allow-execute",{"identifier":"shell:allow-execute","allow":[{"args":["/select,",{"validator":"\\S+"}],"cmd":"explorer"}]}]}}